cloudguard/__init__.py
cloudguard/cli.py
cloudguard/reports.py
cloudguard/scanner.py
cloudguard/checks/__init__.py
cloudguard/checks/base.py
cloudguard/checks/cloudtrail.py
cloudguard/checks/ec2.py
cloudguard/checks/iam.py
cloudguard/checks/s3.py
cloudguard/checks/vpc.py
cloudguard/utils/__init__.py
cloudguard/utils/output.py
cloudguard-1.0.0.dist-info/licenses/LICENSE
cloudguard-1.0.0.dist-info/METADATA
cloudguard-1.0.0.dist-info/WHEEL
cloudguard-1.0.0.dist-info/entry_points.txt
cloudguard-1.0.0.dist-info/top_level.txt
cloudguard-1.0.0.dist-info/RECORD
