Metadata-Version: 2.4
Name: cloudguard
Version: 1.0.0
Summary: AWS Security Compliance Scanner - Automated security scanning aligned with CIS AWS Foundations Benchmark
Author-email: CloudGuard <cloudguard@example.com>
License: MIT
Project-URL: Homepage, https://github.com/yourusername/cloudguard
Project-URL: Documentation, https://github.com/yourusername/cloudguard#readme
Project-URL: Repository, https://github.com/yourusername/cloudguard
Project-URL: Issues, https://github.com/yourusername/cloudguard/issues
Keywords: aws,security,compliance,scanner,cis,cloud,devsecops
Classifier: Development Status :: 4 - Beta
Classifier: Environment :: Console
Classifier: Intended Audience :: Developers
Classifier: Intended Audience :: System Administrators
Classifier: License :: OSI Approved :: MIT License
Classifier: Operating System :: OS Independent
Classifier: Programming Language :: Python :: 3
Classifier: Programming Language :: Python :: 3.8
Classifier: Programming Language :: Python :: 3.9
Classifier: Programming Language :: Python :: 3.10
Classifier: Programming Language :: Python :: 3.11
Classifier: Programming Language :: Python :: 3.12
Classifier: Topic :: Security
Classifier: Topic :: System :: Systems Administration
Requires-Python: >=3.8
License-File: LICENSE
Requires-Dist: boto3>=1.26.0
Requires-Dist: click>=8.0.0
Requires-Dist: rich>=12.0.0
Provides-Extra: dev
Requires-Dist: pytest>=7.0.0; extra == "dev"
Requires-Dist: pytest-cov>=4.0.0; extra == "dev"
Requires-Dist: moto>=4.0.0; extra == "dev"
Requires-Dist: black>=23.0.0; extra == "dev"
Requires-Dist: isort>=5.0.0; extra == "dev"
Requires-Dist: flake8>=6.0.0; extra == "dev"
Dynamic: license-file
